[
  {
    "CaseTypeId": "ET_EnglandWales",
    "CaseFieldID": "nocRemoveRepresentationLandingPageLabel",
    "UserRole": "[CLAIMANTSOLICITOR]",
    "CRUD": "R"
  },
  {
    "CaseTypeId": "ET_EnglandWales",
    "CaseFieldID": "nocRemoveRepresentationLandingPageLabel",
    "UserRole": [
      "[SOLICITORA]",
      "[SOLICITORB]",
      "[SOLICITORC]",
      "[SOLICITORD]",
      "[SOLICITORE]",
      "[SOLICITORF]",
      "[SOLICITORG]",
      "[SOLICITORH]",
      "[SOLICITORI]",
      "[SOLICITORJ]"
    ],
    "CRUD": "R"
  },
  {
    "CaseTypeId": "ET_EnglandWales",
    "CaseFieldID": "nocRemoveRepresentationClaimantSignLabel",
    "UserRole": "[CLAIMANTSOLICITOR]",
    "CRUD": "R"
  },
  {
    "CaseTypeId": "ET_EnglandWales",
    "CaseFieldID": "nocRemoveRepresentationRespondentSignLabel",
    "UserRole": [
      "[SOLICITORA]",
      "[SOLICITORB]",
      "[SOLICITORC]",
      "[SOLICITORD]",
      "[SOLICITORE]",
      "[SOLICITORF]",
      "[SOLICITORG]",
      "[SOLICITORH]",
      "[SOLICITORI]",
      "[SOLICITORJ]"
    ],
    "CRUD": "R"
  },
  {
    "CaseTypeId": "ET_EnglandWales",
    "CaseFieldID": "nocRemoveRepresentationConfirmNoLonger",
    "UserRole": "[CLAIMANTSOLICITOR]",
    "CRUD": "CRU"
  },
  {
    "CaseTypeId": "ET_EnglandWales",
    "CaseFieldID": "nocRemoveRepresentationConfirmNoLonger",
    "UserRole": [
      "[SOLICITORA]",
      "[SOLICITORB]",
      "[SOLICITORC]",
      "[SOLICITORD]",
      "[SOLICITORE]",
      "[SOLICITORF]",
      "[SOLICITORG]",
      "[SOLICITORH]",
      "[SOLICITORI]",
      "[SOLICITORJ]"
    ],
    "CRUD": "CRU"
  },
  {
    "CaseTypeId": "ET_EnglandWales",
    "CaseFieldID": "nocRemoveRepresentationConfirmNotice",
    "UserRole": "[CLAIMANTSOLICITOR]",
    "CRUD": "CRU"
  },
  {
    "CaseTypeId": "ET_EnglandWales",
    "CaseFieldID": "nocRemoveRepresentationConfirmNotice",
    "UserRole": [
      "[SOLICITORA]",
      "[SOLICITORB]",
      "[SOLICITORC]",
      "[SOLICITORD]",
      "[SOLICITORE]",
      "[SOLICITORF]",
      "[SOLICITORG]",
      "[SOLICITORH]",
      "[SOLICITORI]",
      "[SOLICITORJ]"
    ],
    "CRUD": "CRU"
  }
]
